pynscq/__init__.py
pynscq/paths.py
pynscq-2.0.1.data/scripts/list_switch_errors.py
pynscq-2.0.1.data/scripts/list_switch_info.py
pynscq-2.0.1.data/scripts/lsnvswitch.py
pynscq-2.0.1.dist-info/METADATA
pynscq-2.0.1.dist-info/WHEEL
pynscq-2.0.1.dist-info/top_level.txt
pynscq-2.0.1.dist-info/RECORD
