Metadata-Version: 2.1
Name: pynscq
Version: 2.0.1
Summary: Python bindings for the NVSwitch Configuration and Query (NSCQ) library
Home-page: UNKNOWN
Author: NVIDIA Corporation
Author-email: CUDAIssues@nvidia.com
License: UNKNOWN
Keywords: nvidia nvswitch nscq management nvlink
Platform: UNKNOWN
Requires-Python: >=3
